bigo_test/__init__.py
bigo_test/complexity.py
bigo_test/exceptions.py
bigo_test/assertions/__init__.py
bigo_test/assertions/assert_big_o.py
bigo_test/assertions/base_assert.py
bigo_test/assertions/helpers.py
bigo_test-0.2.0.dist-info/LICENSE
bigo_test-0.2.0.dist-info/WHEEL
bigo_test-0.2.0.dist-info/METADATA
bigo_test-0.2.0.dist-info/RECORD
